omnilingual_asr/__init__.py
omnilingual_asr/cards/datasets/example_dataset.yaml
omnilingual_asr/cards/models/rc_models_v1.yaml
omnilingual_asr/cards/models/rc_models_v2.yaml
omnilingual_asr/datasets/__init__.py
omnilingual_asr/datasets/impl/manifest_asr_dataset.py
omnilingual_asr/datasets/impl/mixture_parquet_asr_dataset.py
omnilingual_asr/datasets/interfaces/storage_interface.py
omnilingual_asr/datasets/interfaces/task_interface.py
omnilingual_asr/datasets/storage/manifest_storage.py
omnilingual_asr/datasets/storage/mixture_parquet_storage.py
omnilingual_asr/datasets/tasks/asr_task.py
omnilingual_asr/datasets/tasks/ssl_task.py
omnilingual_asr/datasets/utils/audio.py
omnilingual_asr/datasets/utils/batching.py
omnilingual_asr/datasets/utils/text.py
omnilingual_asr/models/__init__.py
omnilingual_asr/models/inference/__init__.py
omnilingual_asr/models/inference/pipeline.py
omnilingual_asr/models/wav2vec2_asr/__init__.py
omnilingual_asr/models/wav2vec2_asr/config.py
omnilingual_asr/models/wav2vec2_llama/__init__.py
omnilingual_asr/models/wav2vec2_llama/beamsearch.py
omnilingual_asr/models/wav2vec2_llama/config.py
omnilingual_asr/models/wav2vec2_llama/factory.py
omnilingual_asr/models/wav2vec2_llama/fsdp.py
omnilingual_asr/models/wav2vec2_llama/hub.py
omnilingual_asr/models/wav2vec2_llama/interop.py
omnilingual_asr/models/wav2vec2_llama/lang_ids.py
omnilingual_asr/models/wav2vec2_llama/languges_lookup_table.parquet
omnilingual_asr/models/wav2vec2_llama/model.py
omnilingual_asr/models/wav2vec2_llama/syntax.py
omnilingual_asr/models/wav2vec2_ssl/__init__.py
omnilingual_asr/models/wav2vec2_ssl/config.py
omnilingual_asr-0.2.0.dist-info/LICENSE
omnilingual_asr-0.2.0.dist-info/METADATA
omnilingual_asr-0.2.0.dist-info/WHEEL
omnilingual_asr-0.2.0.dist-info/entry_points.txt
omnilingual_asr-0.2.0.dist-info/top_level.txt
omnilingual_asr-0.2.0.dist-info/RECORD
