Metadata-Version: 2.1
Name: omnilingual-asr
Version: 0.2.0
Summary: Omnilingual ASR Modeling Library
Author: Meta AI Research
License: Copyright 2025 (c) Meta Platforms, Inc. and affiliates.
Project-URL: Source, https://github.com/facebookresearch/omnilingual-asr
Project-URL: Tracker, https://github.com/facebookresearch/omnilingual-asr/issues
Keywords: speech recognition,ASR,automatic speech recognition,multilingual,omnilingual,zero-shot,few-shot,speech-to-text,audio processing,wav2vec2,fairseq2,language models,speech technology,CTC,transformer models,beam search,audio transcription,voice recognition
Classifier: Topic :: Scientific/Engineering
Classifier: Development Status :: 4 - Beta
Requires-Python: <=3.12,>=3.10
License-File: LICENSE
Requires-Dist: fairseq2[arrow]<=0.6.0,>=0.5.2
Requires-Dist: pyarrow>=20.0.0
Requires-Dist: torch
Requires-Dist: torchaudio
Requires-Dist: numba
Requires-Dist: pandas
Requires-Dist: numpy
Requires-Dist: kenlm
Requires-Dist: polars>=1.29.0
Provides-Extra: data
Requires-Dist: fire; extra == "data"
Requires-Dist: transformers; extra == "data"
Requires-Dist: datasets~=3.6.0; extra == "data"
Requires-Dist: ray>=2.49.0; extra == "data"
Requires-Dist: soundfile>=0.13.1; extra == "data"
Requires-Dist: librosa>=0.11.0; extra == "data"
Requires-Dist: unidecode; extra == "data"
Requires-Dist: uroman; extra == "data"
Requires-Dist: retrying; extra == "data"
Provides-Extra: dev
Requires-Dist: black~=25.1; extra == "dev"
Requires-Dist: flake8~=7.1; extra == "dev"
Requires-Dist: flake8-pyi~=24.6; extra == "dev"
Requires-Dist: flake8-pyproject~=1.2; extra == "dev"
Requires-Dist: isort~=6.0; extra == "dev"
Requires-Dist: mypy~=1.15.0; extra == "dev"
Requires-Dist: pandas-stubs~=2.2.3; extra == "dev"
Requires-Dist: pyarrow-stubs~=20.0; extra == "dev"
Requires-Dist: pytest~=8.3; extra == "dev"
Requires-Dist: shellcheck-py~=0.9; extra == "dev"
Requires-Dist: types-tqdm~=4.67.0; extra == "dev"
Requires-Dist: types-editdistance~=0.6; extra == "dev"
Requires-Dist: types-psutil~=5.9; extra == "dev"
Requires-Dist: types-setuptools~=75.8; extra == "dev"
